processcube_sdk/__init__.py
processcube_sdk/__main__.py
processcube_sdk/configuration/__init__.py
processcube_sdk/configuration/config.py
processcube_sdk/configuration/config_accessor.py
processcube_sdk/database/__init__.py
processcube_sdk/database/orm_helper.py
processcube_sdk/debugging/__init__.py
processcube_sdk/debugging/start_debugging.py
processcube_sdk/external_tasks/__init__.py
processcube_sdk/external_tasks/__main__.py
processcube_sdk/external_tasks/base_handler.py
processcube_sdk/external_tasks/external_task_cmd.py
processcube_sdk/external_tasks/jupyter_handler.py
processcube_sdk/external_tasks/skip_handler.py
processcube_sdk/external_tasks/check_running_process_instance/__init__.py
processcube_sdk/external_tasks/check_running_process_instance/__main__.py
processcube_sdk/external_tasks/check_running_process_instance/check_running_process_instance_handler.py
processcube_sdk/fastapi/__init__.py
processcube_sdk/fastapi/auth/__init__.py
processcube_sdk/fastapi/auth/google.py
processcube_sdk/helpers/__init__.py
processcube_sdk/helpers/string_helpers.py
processcube_sdk/jupyter/__init__.py
processcube_sdk/jupyter/notebook_runner.py
processcube_sdk/logging/__init__.py
processcube_sdk/logging/setup.py
processcube_sdk/oauth/__init__.py
processcube_sdk/oauth/identity_provider.py
processcube_sdk/xlwings_helpers/__init__.py
processcube_sdk-5.1.0.dist-info/LICENSE
processcube_sdk-5.1.0.dist-info/METADATA
processcube_sdk-5.1.0.dist-info/WHEEL
processcube_sdk-5.1.0.dist-info/top_level.txt
processcube_sdk-5.1.0.dist-info/RECORD
