Metadata-Version: 2.2
Name: processcube_sdk
Version: 5.1.0
Summary: Some tools and defaults to program for the ProcessCube.
Home-page: https://github.com/5minds/processcube_sdk.py
Author: 5Minds IT-Solutions GmbH & Co. KG
Author-email: processcube@5minds.de
Keywords: sdk processcube bpmm external-tasks process-management etw
Classifier: Programming Language :: Python :: 3
Classifier: License :: OSI Approved :: MIT License
Classifier: Operating System :: OS Independent
License-File: LICENSE
Requires-Dist: wheel==0.41.3
Requires-Dist: typer>=0.9.0
Requires-Dist: debugpy>=1.8.0
Requires-Dist: processcube-client==5.0.0
Requires-Dist: papermill==2.5.0
Requires-Dist: scrapbook==0.5.0
Requires-Dist: pandas==1.5.1
Requires-Dist: numpy==1.26.2
Requires-Dist: sqlalchemy==1.4.50
Requires-Dist: stringcase==1.2.0
Requires-Dist: fastapi>=0.104.1
Requires-Dist: google-api-python-client==2.66.0
Requires-Dist: google-auth-httplib2==0.1.0
Requires-Dist: google-auth-oauthlib==0.7.1
Requires-Dist: oauth2-client==1.2.1
Requires-Dist: tenacity==8.1.0
Dynamic: author
Dynamic: author-email
Dynamic: classifier
Dynamic: description
Dynamic: description-content-type
Dynamic: home-page
Dynamic: keywords
Dynamic: requires-dist
Dynamic: summary
